{
	"workbench.iconTheme": "vscode-icons",
	"vsicons.projectDetection.autoReload": true,
	"terminal.integrated.shell.windows": "C:\\WINDOWS\\Sysnative\\cmd.exe",
	"window.menuBarVisibility": "default",
	"workbench.sideBar.location": "left",
	"workbench.activityBar.visible": true,
	"editor.minimap.enabled": false,
	"window.zoomLevel": 0,
	"html.format.wrapLineLength": 0,
	"html.format.indentInnerHtml": true,
	"workbench.startupEditor": "none",
	"html.format.preserveNewLines": true,
	"editor.formatOnSave": false,
	"editor.detectIndentation": false,
	"editor.tabSize": 2,
	"editor.insertSpaces": false,
	"files.autoSave": "off",
	"html.format.unformatted": "null",
	"git.autofetch": true,
	"git.confirmSync": false
}
